asoq/__init__.py
asoq/asoq.py
asoq-0.1.0.dist-info/METADATA
asoq-0.1.0.dist-info/WHEEL
asoq-0.1.0.dist-info/top_level.txt
asoq-0.1.0.dist-info/RECORD
