Metadata-Version: 2.4
Name: asoq
Version: 0.1.0
Summary: An asynchronous simple queue for background tasks in Python.
Author-email: Bohdan Riabunets <bearablyk@gmail.com>
License-Expression: MIT
Project-URL: Homepage, https://github.com/bearablyk/asoq
Project-URL: Issues, https://github.com/bearablyk/asoq/issues
Classifier: Programming Language :: Python :: 3
Classifier: Operating System :: OS Independent
Requires-Python: >=3.8
